README.txt
setup.py
WsgiUnproxy.egg-info/PKG-INFO
WsgiUnproxy.egg-info/SOURCES.txt
WsgiUnproxy.egg-info/dependency_links.txt
WsgiUnproxy.egg-info/entry_points.txt
WsgiUnproxy.egg-info/top_level.txt
WsgiUnproxy.egg-info/zip-safe
wsgiunproxy/__init__.py