Metadata-Version: 1.0
Name: WsgiUnproxy
Version: 1.0
Summary: Unproxy WSGI middleware
Home-page: https://bitbucket.org/kwi/wsgiunproxy/
Author: Søren Løvborg
Author-email: kwi@kwi.dk
License: Public Domain
Platform: UNKNOWN
Classifier: Development Status :: 5 - Production/Stable
Classifier: Intended Audience :: Developers
Classifier: Intended Audience :: System Administrators
Classifier: License :: Public Domain
Classifier: Operating System :: OS Independent
Classifier: Programming Language :: Python
Classifier: Programming Language :: Python :: 3
Classifier: Topic :: Internet :: Proxy Servers
Classifier: Topic :: Internet :: WWW/HTTP
Classifier: Topic :: Internet :: WWW/HTTP :: WSGI
Classifier: Topic :: Internet :: WWW/HTTP :: WSGI :: Middleware
